seotools/__init__.py
seotools/app.py
seotools/crawl_bot_validation.py
seotools/forecast.py
seotools/logs.py
seotools/topics.py
seotools/links/__init__.py
seotools/links/broken.py
seotools-0.1.2.dist-info/LICENSE
seotools-0.1.2.dist-info/METADATA
seotools-0.1.2.dist-info/WHEEL
seotools-0.1.2.dist-info/top_level.txt
seotools-0.1.2.dist-info/RECORD
